holmes_extractor/__init__.py
holmes_extractor/about.py
holmes_extractor/classification.py
holmes_extractor/config.cfg
holmes_extractor/consoles.py
holmes_extractor/errors.py
holmes_extractor/manager.py
holmes_extractor/ontology.py
holmes_extractor/parsing.py
holmes_extractor/structural_matching.py
holmes_extractor/topic_matching.py
holmes_extractor/lang/__init__.py
holmes_extractor/lang/de/__init__.py
holmes_extractor/lang/de/language_specific_rules.py
holmes_extractor/lang/de/data/__init__.py
holmes_extractor/lang/de/data/derivation.csv
holmes_extractor/lang/en/__init__.py
holmes_extractor/lang/en/language_specific_rules.py
holmes_extractor/lang/en/data/__init__.py
holmes_extractor/lang/en/data/derivation.csv
holmes_extractor/word_matching/derivation.py
holmes_extractor/word_matching/direct.py
holmes_extractor/word_matching/embedding.py
holmes_extractor/word_matching/entity.py
holmes_extractor/word_matching/entity_embedding.py
holmes_extractor/word_matching/general.py
holmes_extractor/word_matching/ontology.py
holmes_extractor/word_matching/question.py
holmes_extractor-4.2.1.dist-info/LICENSE
holmes_extractor-4.2.1.dist-info/METADATA
holmes_extractor-4.2.1.dist-info/WHEEL
holmes_extractor-4.2.1.dist-info/top_level.txt
holmes_extractor-4.2.1.dist-info/RECORD
