Metadata-Version: 2.1
Name: holmes-extractor
Version: 4.2.1
Summary: Information extraction from English and German texts based on predicate logic
Home-page: https://github.com/richardpaulhudson/holmes-extractor
Author: Richard Paul Hudson
Author-email: hudsonrichardpaul@gmail.com
License: MIT
Keywords: nlp,information-extraction,spacy,spacy-extension,python,machine-learning,ontology,semantics
Classifier: Development Status :: 5 - Production/Stable
Classifier: Intended Audience :: Developers
Classifier: Intended Audience :: Financial and Insurance Industry
Classifier: Intended Audience :: Healthcare Industry
Classifier: Intended Audience :: Information Technology
Classifier: Intended Audience :: Legal Industry
Classifier: Intended Audience :: Other Audience
Classifier: Intended Audience :: Education
Classifier: Intended Audience :: Science/Research
Classifier: License :: OSI Approved :: MIT License
Classifier: Natural Language :: English
Classifier: Natural Language :: German
Classifier: Programming Language :: Python :: 3
Classifier: Programming Language :: Python :: 3.6
Classifier: Programming Language :: Python :: 3.7
Classifier: Programming Language :: Python :: 3.8
Classifier: Programming Language :: Python :: 3.9
Classifier: Programming Language :: Python :: 3.10
Classifier: Programming Language :: Python :: 3.11
Classifier: Topic :: Scientific/Engineering :: Artificial Intelligence
Classifier: Topic :: Scientific/Engineering :: Information Analysis
Classifier: Topic :: Text Processing :: Linguistic
Requires-Python: <3.12,>=3.6
License-File: LICENSE
Requires-Dist: spacy (<3.6.0,>=3.1.0)
Requires-Dist: coreferee (>=1.4.1)
Requires-Dist: rdflib
